{
 "player_id": 650490,
 "player_name": "Yandy D\u00edaz",
 "team": "TB",
 "as_of": "2026-07-18",
 "form": {
  "streak": 0,
  "frequency": 0.286,
  "slopes": {
   "max_ev": 2.329,
   "parks_sum": 0.107,
   "near_hr": 0.188
  },
  "intensity": 0.408,
  "expectancy_score": 20.8,
  "last_appearance": "2026-07-12"
 },
 "days": [
  {
   "date": "2026-07-12",
   "bbe": 4,
   "hr": 0,
   "near_hr_any": 0,
   "near_hr_xbh": 0,
   "near_hr_distance": 0,
   "near_hr_parks": 0,
   "near_hr_barrel": 0,
   "would_be_hr_parks_sum": 0,
   "max_ev": 110.2,
   "max_distance": 263.0,
   "max_barrel_score": 55.6,
   "temp_f": 72.0,
   "wind_mph": 0.0,
   "wind_dir": "none",
   "weather_condition": "Dome"
  },
  {
   "date": "2026-07-11",
   "bbe": 5,
   "hr": 0,
   "near_hr_any": 3,
   "near_hr_xbh": 1,
   "near_hr_distance": 2,
   "near_hr_parks": 1,
   "near_hr_barrel": 3,
   "would_be_hr_parks_sum": 7,
   "max_ev": 106.8,
   "max_distance": 392.0,
   "max_barrel_score": 84.0,
   "temp_f": 72.0,
   "wind_mph": 0.0,
   "wind_dir": "none",
   "weather_condition": "Dome"
  },
  {
   "date": "2026-07-10",
   "bbe": 4,
   "hr": 0,
   "near_hr_any": 0,
   "near_hr_xbh": 0,
   "near_hr_distance": 0,
   "near_hr_parks": 0,
   "near_hr_barrel": 0,
   "would_be_hr_parks_sum": 0,
   "max_ev": 102.9,
   "max_distance": 288.0,
   "max_barrel_score": 61.7,
   "temp_f": 72.0,
   "wind_mph": 0.0,
   "wind_dir": "none",
   "weather_condition": "Dome"
  },
  {
   "date": "2026-07-09",
   "bbe": 3,
   "hr": 0,
   "near_hr_any": 0,
   "near_hr_xbh": 0,
   "near_hr_distance": 0,
   "near_hr_parks": 0,
   "near_hr_barrel": 0,
   "would_be_hr_parks_sum": 0,
   "max_ev": 101.4,
   "max_distance": 23.0,
   "max_barrel_score": 28.3,
   "temp_f": 72.0,
   "wind_mph": 0.0,
   "wind_dir": "none",
   "weather_condition": "Dome"
  },
  {
   "date": "2026-07-08",
   "bbe": 4,
   "hr": 0,
   "near_hr_any": 1,
   "near_hr_xbh": 1,
   "near_hr_distance": 1,
   "near_hr_parks": 1,
   "near_hr_barrel": 1,
   "would_be_hr_parks_sum": 11,
   "max_ev": 104.8,
   "max_distance": 373.0,
   "max_barrel_score": 73.9,
   "temp_f": 72.0,
   "wind_mph": 0.0,
   "wind_dir": "none",
   "weather_condition": "Dome"
  },
  {
   "date": "2026-07-07",
   "bbe": 4,
   "hr": 1,
   "near_hr_any": 0,
   "near_hr_xbh": 0,
   "near_hr_distance": 0,
   "near_hr_parks": 0,
   "near_hr_barrel": 0,
   "would_be_hr_parks_sum": 0,
   "max_ev": 103.7,
   "max_distance": 368.0,
   "max_barrel_score": 74.4,
   "temp_f": 72.0,
   "wind_mph": 0.0,
   "wind_dir": "none",
   "weather_condition": "Dome"
  },
  {
   "date": "2026-07-06",
   "bbe": 3,
   "hr": 0,
   "near_hr_any": 0,
   "near_hr_xbh": 0,
   "near_hr_distance": 0,
   "near_hr_parks": 0,
   "near_hr_barrel": 0,
   "would_be_hr_parks_sum": 0,
   "max_ev": 89.9,
   "max_distance": 181.0,
   "max_barrel_score": 29.6,
   "temp_f": 72.0,
   "wind_mph": 0.0,
   "wind_dir": "none",
   "weather_condition": "Dome"
  },
  {
   "date": "2026-07-05",
   "bbe": 1,
   "hr": 0,
   "near_hr_any": 0,
   "near_hr_xbh": 0,
   "near_hr_distance": 0,
   "near_hr_parks": 0,
   "near_hr_barrel": 0,
   "would_be_hr_parks_sum": 0,
   "max_ev": 79.2,
   "max_distance": 21.0,
   "max_barrel_score": 9.6,
   "temp_f": 73.0,
   "wind_mph": 0.0,
   "wind_dir": "none",
   "weather_condition": "Roof Closed"
  }
 ],
 "events": [
  {
   "game_pk": 822951,
   "date": "2026-07-12",
   "player_id": 650490,
   "player_name": "Yandy D\u00edaz",
   "team": "TB",
   "opponent": "SEA",
   "result": "Single",
   "exit_velocity": 96.9,
   "launch_angle": 13.0,
   "hit_distance": 263.0,
   "hc_x": 202.43,
   "hc_y": 106.16,
   "would_be_hr_count": 0,
   "inning": 3,
   "play_id": "b860931c-70dd-3aa1-b7dc-7d3d130740ea",
   "venue_id": 12,
   "venue_name": "Tropicana Field",
   "temp_f": 72.0,
   "wind_mph": 0.0,
   "wind_dir": "none",
   "weather_condition": "Dome",
   "distance_flag": false,
   "would_be_hr_flag": false,
   "barrel_score": 55.6,
   "barrel_flag": false,
   "is_home_run": false,
   "is_near_hr": false
  },
  {
   "game_pk": 822951,
   "date": "2026-07-12",
   "player_id": 650490,
   "player_name": "Yandy D\u00edaz",
   "team": "TB",
   "opponent": "SEA",
   "result": "Single",
   "exit_velocity": 110.2,
   "launch_angle": -12.0,
   "hit_distance": 8.0,
   "hc_x": 116.79,
   "hc_y": 111.9,
   "would_be_hr_count": 0,
   "inning": 8,
   "play_id": "a7978baf-2612-37da-a9b8-6912026e4101",
   "venue_id": 12,
   "venue_name": "Tropicana Field",
   "temp_f": 72.0,
   "wind_mph": 0.0,
   "wind_dir": "none",
   "weather_condition": "Dome",
   "distance_flag": false,
   "would_be_hr_flag": false,
   "barrel_score": 36.3,
   "barrel_flag": false,
   "is_home_run": false,
   "is_near_hr": false
  },
  {
   "game_pk": 822951,
   "date": "2026-07-12",
   "player_id": 650490,
   "player_name": "Yandy D\u00edaz",
   "team": "TB",
   "opponent": "SEA",
   "result": "Groundout",
   "exit_velocity": 107.2,
   "launch_angle": -10.0,
   "hit_distance": 13.0,
   "hc_x": 128.5,
   "hc_y": 174.49,
   "would_be_hr_count": 0,
   "inning": 1,
   "play_id": "cfa6edaa-a514-39fc-ab99-0d242ba5f78b",
   "venue_id": 12,
   "venue_name": "Tropicana Field",
   "temp_f": 72.0,
   "wind_mph": 0.0,
   "wind_dir": "none",
   "weather_condition": "Dome",
   "distance_flag": false,
   "would_be_hr_flag": false,
   "barrel_score": 33.9,
   "barrel_flag": false,
   "is_home_run": false,
   "is_near_hr": false
  },
  {
   "game_pk": 822951,
   "date": "2026-07-12",
   "player_id": 650490,
   "player_name": "Yandy D\u00edaz",
   "team": "TB",
   "opponent": "SEA",
   "result": "Forceout",
   "exit_velocity": 85.2,
   "launch_angle": -11.0,
   "hit_distance": 10.0,
   "hc_x": 118.87,
   "hc_y": 152.7,
   "would_be_hr_count": 0,
   "inning": 5,
   "play_id": "cd11ec7e-f1e7-3cd0-841f-6cc569d974df",
   "venue_id": 12,
   "venue_name": "Tropicana Field",
   "temp_f": 72.0,
   "wind_mph": 0.0,
   "wind_dir": "none",
   "weather_condition": "Dome",
   "distance_flag": false,
   "would_be_hr_flag": false,
   "barrel_score": 14.2,
   "barrel_flag": false,
   "is_home_run": false,
   "is_near_hr": false
  },
  {
   "game_pk": 822953,
   "date": "2026-07-11",
   "player_id": 650490,
   "player_name": "Yandy D\u00edaz",
   "team": "TB",
   "opponent": "SEA",
   "result": "Double",
   "exit_velocity": 103.2,
   "launch_angle": 29.0,
   "hit_distance": 392.0,
   "hc_x": 91.21,
   "hc_y": 44.69,
   "would_be_hr_count": 7,
   "inning": 3,
   "play_id": "af52ec72-8295-3392-9051-db0c854af732",
   "venue_id": 12,
   "venue_name": "Tropicana Field",
   "temp_f": 72.0,
   "wind_mph": 0.0,
   "wind_dir": "none",
   "weather_condition": "Dome",
   "distance_flag": true,
   "would_be_hr_flag": true,
   "barrel_score": 84.0,
   "barrel_flag": true,
   "is_home_run": false,
   "is_near_hr": true
  },
  {
   "game_pk": 822953,
   "date": "2026-07-11",
   "player_id": 650490,
   "player_name": "Yandy D\u00edaz",
   "team": "TB",
   "opponent": "SEA",
   "result": "Flyout",
   "exit_velocity": 106.5,
   "launch_angle": 36.0,
   "hit_distance": 391.0,
   "hc_x": 126.0,
   "hc_y": 41.25,
   "would_be_hr_count": 0,
   "inning": 1,
   "play_id": "cf0955ae-85cb-3e1c-8282-0c399f66e987",
   "venue_id": 12,
   "venue_name": "Tropicana Field",
   "temp_f": 72.0,
   "wind_mph": 0.0,
   "wind_dir": "none",
   "weather_condition": "Dome",
   "distance_flag": true,
   "would_be_hr_flag": false,
   "barrel_score": 79.2,
   "barrel_flag": true,
   "is_home_run": false,
   "is_near_hr": true
  },
  {
   "game_pk": 822953,
   "date": "2026-07-11",
   "player_id": 650490,
   "player_name": "Yandy D\u00edaz",
   "team": "TB",
   "opponent": "SEA",
   "result": "Lineout",
   "exit_velocity": 106.8,
   "launch_angle": 16.0,
   "hit_distance": 335.0,
   "hc_x": 195.5,
   "hc_y": 83.18,
   "would_be_hr_count": 0,
   "inning": 7,
   "play_id": "d018a327-93f7-34f1-80c3-3d0cd495e4c4",
   "venue_id": 12,
   "venue_name": "Tropicana Field",
   "temp_f": 72.0,
   "wind_mph": 0.0,
   "wind_dir": "none",
   "weather_condition": "Dome",
   "distance_flag": false,
   "would_be_hr_flag": false,
   "barrel_score": 72.5,
   "barrel_flag": true,
   "is_home_run": false,
   "is_near_hr": true
  },
  {
   "game_pk": 822953,
   "date": "2026-07-11",
   "player_id": 650490,
   "player_name": "Yandy D\u00edaz",
   "team": "TB",
   "opponent": "SEA",
   "result": "Groundout",
   "exit_velocity": 92.5,
   "launch_angle": -30.0,
   "hit_distance": 5.0,
   "hc_x": 100.63,
   "hc_y": 164.35,
   "would_be_hr_count": 0,
   "inning": 8,
   "play_id": "8b3c4689-5d11-300a-80ce-1d67cc10346b",
   "venue_id": 12,
   "venue_name": "Tropicana Field",
   "temp_f": 72.0,
   "wind_mph": 0.0,
   "wind_dir": "none",
   "weather_condition": "Dome",
   "distance_flag": false,
   "would_be_hr_flag": false,
   "barrel_score": 20.3,
   "barrel_flag": false,
   "is_home_run": false,
   "is_near_hr": false
  },
  {
   "game_pk": 822953,
   "date": "2026-07-11",
   "player_id": 650490,
   "player_name": "Yandy D\u00edaz",
   "team": "TB",
   "opponent": "SEA",
   "result": "Pop Out",
   "exit_velocity": 68.9,
   "launch_angle": 70.0,
   "hit_distance": 110.0,
   "hc_x": 172.08,
   "hc_y": 192.22,
   "would_be_hr_count": 0,
   "inning": 4,
   "play_id": "35ffc8b3-bb0e-3ab8-bdf8-7f415dbc035c",
   "venue_id": 12,
   "venue_name": "Tropicana Field",
   "temp_f": 72.0,
   "wind_mph": 0.0,
   "wind_dir": "none",
   "weather_condition": "Dome",
   "distance_flag": false,
   "would_be_hr_flag": false,
   "barrel_score": 7.3,
   "barrel_flag": false,
   "is_home_run": false,
   "is_near_hr": false
  },
  {
   "game_pk": 822955,
   "date": "2026-07-10",
   "player_id": 650490,
   "player_name": "Yandy D\u00edaz",
   "team": "TB",
   "opponent": "SEA",
   "result": "Lineout",
   "exit_velocity": 84.7,
   "launch_angle": 28.0,
   "hit_distance": 288.0,
   "hc_x": 184.82,
   "hc_y": 99.66,
   "would_be_hr_count": 0,
   "inning": 8,
   "play_id": "11246d2c-85f1-3a8e-9c16-62d5624bc88d",
   "venue_id": 12,
   "venue_name": "Tropicana Field",
   "temp_f": 72.0,
   "wind_mph": 0.0,
   "wind_dir": "none",
   "weather_condition": "Dome",
   "distance_flag": false,
   "would_be_hr_flag": false,
   "barrel_score": 61.7,
   "barrel_flag": false,
   "is_home_run": false,
   "is_near_hr": false
  },
  {
   "game_pk": 822955,
   "date": "2026-07-10",
   "player_id": 650490,
   "player_name": "Yandy D\u00edaz",
   "team": "TB",
   "opponent": "SEA",
   "result": "Lineout",
   "exit_velocity": 80.1,
   "launch_angle": 20.0,
   "hit_distance": 267.0,
   "hc_x": 82.21,
   "hc_y": 101.83,
   "would_be_hr_count": 0,
   "inning": 4,
   "play_id": "660cda13-4978-301f-9ff5-f72a2aad458a",
   "venue_id": 12,
   "venue_name": "Tropicana Field",
   "temp_f": 72.0,
   "wind_mph": 0.0,
   "wind_dir": "none",
   "weather_condition": "Dome",
   "distance_flag": false,
   "would_be_hr_flag": false,
   "barrel_score": 48.6,
   "barrel_flag": false,
   "is_home_run": false,
   "is_near_hr": false
  },
  {
   "game_pk": 822955,
   "date": "2026-07-10",
   "player_id": 650490,
   "player_name": "Yandy D\u00edaz",
   "team": "TB",
   "opponent": "SEA",
   "result": "Groundout",
   "exit_velocity": 102.9,
   "launch_angle": -19.0,
   "hit_distance": 11.0,
   "hc_x": 113.3,
   "hc_y": 147.63,
   "would_be_hr_count": 0,
   "inning": 1,
   "play_id": "69c96775-5f6c-3ae9-8712-31d5cdb2d7be",
   "venue_id": 12,
   "venue_name": "Tropicana Field",
   "temp_f": 72.0,
   "wind_mph": 0.0,
   "wind_dir": "none",
   "weather_condition": "Dome",
   "distance_flag": false,
   "would_be_hr_flag": false,
   "barrel_score": 30.0,
   "barrel_flag": false,
   "is_home_run": false,
   "is_near_hr": false
  },
  {
   "game_pk": 822955,
   "date": "2026-07-10",
   "player_id": 650490,
   "player_name": "Yandy D\u00edaz",
   "team": "TB",
   "opponent": "SEA",
   "result": "Pop Out",
   "exit_velocity": 71.5,
   "launch_angle": 76.0,
   "hit_distance": 89.0,
   "hc_x": 91.51,
   "hc_y": 190.19,
   "would_be_hr_count": 0,
   "inning": 2,
   "play_id": "eb5e62aa-9bfd-3879-90c0-ea09fd724f5b",
   "venue_id": 12,
   "venue_name": "Tropicana Field",
   "temp_f": 72.0,
   "wind_mph": 0.0,
   "wind_dir": "none",
   "weather_condition": "Dome",
   "distance_flag": false,
   "would_be_hr_flag": false,
   "barrel_score": 7.3,
   "barrel_flag": false,
   "is_home_run": false,
   "is_near_hr": false
  },
  {
   "game_pk": 822954,
   "date": "2026-07-09",
   "player_id": 650490,
   "player_name": "Yandy D\u00edaz",
   "team": "TB",
   "opponent": "NYY",
   "result": "Single",
   "exit_velocity": 101.4,
   "launch_angle": -27.0,
   "hit_distance": 6.0,
   "hc_x": 83.01,
   "hc_y": 114.74,
   "would_be_hr_count": 0,
   "inning": 3,
   "play_id": "467cac60-f6d6-3490-af4c-cb2fcf87bce0",
   "venue_id": 12,
   "venue_name": "Tropicana Field",
   "temp_f": 72.0,
   "wind_mph": 0.0,
   "wind_dir": "none",
   "weather_condition": "Dome",
   "distance_flag": false,
   "would_be_hr_flag": false,
   "barrel_score": 28.3,
   "barrel_flag": false,
   "is_home_run": false,
   "is_near_hr": false
  },
  {
   "game_pk": 822954,
   "date": "2026-07-09",
   "player_id": 650490,
   "player_name": "Yandy D\u00edaz",
   "team": "TB",
   "opponent": "NYY",
   "result": "Groundout",
   "exit_velocity": 100.5,
   "launch_angle": -23.0,
   "hit_distance": 7.0,
   "hc_x": 116.29,
   "hc_y": 126.76,
   "would_be_hr_count": 0,
   "inning": 5,
   "play_id": "478b1d67-a666-3f38-9fc9-a507faf38744",
   "venue_id": 12,
   "venue_name": "Tropicana Field",
   "temp_f": 72.0,
   "wind_mph": 0.0,
   "wind_dir": "none",
   "weather_condition": "Dome",
   "distance_flag": false,
   "would_be_hr_flag": false,
   "barrel_score": 27.6,
   "barrel_flag": false,
   "is_home_run": false,
   "is_near_hr": false
  },
  {
   "game_pk": 822954,
   "date": "2026-07-09",
   "player_id": 650490,
   "player_name": "Yandy D\u00edaz",
   "team": "TB",
   "opponent": "NYY",
   "result": "Forceout",
   "exit_velocity": 92.7,
   "launch_angle": -6.0,
   "hit_distance": 23.0,
   "hc_x": 124.95,
   "hc_y": 180.06,
   "would_be_hr_count": 0,
   "inning": 6,
   "play_id": "329ad43a-c23b-3a1f-b7bc-fd0c4ee0e555",
   "venue_id": 12,
   "venue_name": "Tropicana Field",
   "temp_f": 72.0,
   "wind_mph": 0.0,
   "wind_dir": "none",
   "weather_condition": "Dome",
   "distance_flag": false,
   "would_be_hr_flag": false,
   "barrel_score": 21.7,
   "barrel_flag": false,
   "is_home_run": false,
   "is_near_hr": false
  },
  {
   "game_pk": 822957,
   "date": "2026-07-08",
   "player_id": 650490,
   "player_name": "Yandy D\u00edaz",
   "team": "TB",
   "opponent": "NYY",
   "result": "Double",
   "exit_velocity": 95.7,
   "launch_angle": 24.0,
   "hit_distance": 373.0,
   "hc_x": 67.66,
   "hc_y": 75.7,
   "would_be_hr_count": 11,
   "inning": 3,
   "play_id": "d7324921-0f8b-3a80-a925-c46eab9dcc34",
   "venue_id": 12,
   "venue_name": "Tropicana Field",
   "temp_f": 72.0,
   "wind_mph": 0.0,
   "wind_dir": "none",
   "weather_condition": "Dome",
   "distance_flag": true,
   "would_be_hr_flag": true,
   "barrel_score": 73.9,
   "barrel_flag": true,
   "is_home_run": false,
   "is_near_hr": true
  },
  {
   "game_pk": 822957,
   "date": "2026-07-08",
   "player_id": 650490,
   "player_name": "Yandy D\u00edaz",
   "team": "TB",
   "opponent": "NYY",
   "result": "Single",
   "exit_velocity": 94.7,
   "launch_angle": 13.0,
   "hit_distance": 249.0,
   "hc_x": 125.91,
   "hc_y": 69.91,
   "would_be_hr_count": 0,
   "inning": 5,
   "play_id": "f4421f80-bd87-3026-bbb4-5d07c73f0f1b",
   "venue_id": 12,
   "venue_name": "Tropicana Field",
   "temp_f": 72.0,
   "wind_mph": 0.0,
   "wind_dir": "none",
   "weather_condition": "Dome",
   "distance_flag": false,
   "would_be_hr_flag": false,
   "barrel_score": 52.7,
   "barrel_flag": false,
   "is_home_run": false,
   "is_near_hr": false
  },
  {
   "game_pk": 822957,
   "date": "2026-07-08",
   "player_id": 650490,
   "player_name": "Yandy D\u00edaz",
   "team": "TB",
   "opponent": "NYY",
   "result": "Single",
   "exit_velocity": 104.8,
   "launch_angle": -17.0,
   "hit_distance": 6.0,
   "hc_x": 127.82,
   "hc_y": 103.14,
   "would_be_hr_count": 0,
   "inning": 1,
   "play_id": "b5013417-af57-3854-9be0-e1ce09cb1f53",
   "venue_id": 12,
   "venue_name": "Tropicana Field",
   "temp_f": 72.0,
   "wind_mph": 0.0,
   "wind_dir": "none",
   "weather_condition": "Dome",
   "distance_flag": false,
   "would_be_hr_flag": false,
   "barrel_score": 31.3,
   "barrel_flag": false,
   "is_home_run": false,
   "is_near_hr": false
  },
  {
   "game_pk": 822957,
   "date": "2026-07-08",
   "player_id": 650490,
   "player_name": "Yandy D\u00edaz",
   "team": "TB",
   "opponent": "NYY",
   "result": "Single",
   "exit_velocity": 93.5,
   "launch_angle": -7.0,
   "hit_distance": 17.0,
   "hc_x": 172.59,
   "hc_y": 104.56,
   "would_be_hr_count": 0,
   "inning": 7,
   "play_id": "3d4bb18a-eeac-362f-8fac-0cd2e6ebc6b1",
   "venue_id": 12,
   "venue_name": "Tropicana Field",
   "temp_f": 72.0,
   "wind_mph": 0.0,
   "wind_dir": "none",
   "weather_condition": "Dome",
   "distance_flag": false,
   "would_be_hr_flag": false,
   "barrel_score": 22.0,
   "barrel_flag": false,
   "is_home_run": false,
   "is_near_hr": false
  },
  {
   "game_pk": 822956,
   "date": "2026-07-07",
   "player_id": 650490,
   "player_name": "Yandy D\u00edaz",
   "team": "TB",
   "opponent": "NYY",
   "result": "Home Run",
   "exit_velocity": 97.9,
   "launch_angle": 32.0,
   "hit_distance": 368.0,
   "hc_x": 205.07,
   "hc_y": 72.8,
   "would_be_hr_count": 23,
   "inning": 4,
   "play_id": "8c6e14e4-51fd-37d9-b431-f69e6c66a62f",
   "venue_id": 12,
   "venue_name": "Tropicana Field",
   "temp_f": 72.0,
   "wind_mph": 0.0,
   "wind_dir": "none",
   "weather_condition": "Dome",
   "distance_flag": false,
   "would_be_hr_flag": false,
   "barrel_score": 74.4,
   "barrel_flag": false,
   "is_home_run": true,
   "is_near_hr": false
  },
  {
   "game_pk": 822956,
   "date": "2026-07-07",
   "player_id": 650490,
   "player_name": "Yandy D\u00edaz",
   "team": "TB",
   "opponent": "NYY",
   "result": "Single",
   "exit_velocity": 103.7,
   "launch_angle": 4.0,
   "hit_distance": 104.0,
   "hc_x": 86.44,
   "hc_y": 103.04,
   "would_be_hr_count": 0,
   "inning": 2,
   "play_id": "6432e248-bfc4-3109-8123-a9654e2f3c5a",
   "venue_id": 12,
   "venue_name": "Tropicana Field",
   "temp_f": 72.0,
   "wind_mph": 0.0,
   "wind_dir": "none",
   "weather_condition": "Dome",
   "distance_flag": false,
   "would_be_hr_flag": false,
   "barrel_score": 41.3,
   "barrel_flag": false,
   "is_home_run": false,
   "is_near_hr": false
  },
  {
   "game_pk": 822956,
   "date": "2026-07-07",
   "player_id": 650490,
   "player_name": "Yandy D\u00edaz",
   "team": "TB",
   "opponent": "NYY",
   "result": "Groundout",
   "exit_velocity": 103.1,
   "launch_angle": -11.0,
   "hit_distance": 11.0,
   "hc_x": 119.1,
   "hc_y": 136.71,
   "would_be_hr_count": 0,
   "inning": 1,
   "play_id": "2ca99814-1129-3db8-80f7-1b2c3ee8fe83",
   "venue_id": 12,
   "venue_name": "Tropicana Field",
   "temp_f": 72.0,
   "wind_mph": 0.0,
   "wind_dir": "none",
   "weather_condition": "Dome",
   "distance_flag": false,
   "would_be_hr_flag": false,
   "barrel_score": 30.2,
   "barrel_flag": false,
   "is_home_run": false,
   "is_near_hr": false
  },
  {
   "game_pk": 822956,
   "date": "2026-07-07",
   "player_id": 650490,
   "player_name": "Yandy D\u00edaz",
   "team": "TB",
   "opponent": "NYY",
   "result": "Groundout",
   "exit_velocity": 58.3,
   "launch_angle": -19.0,
   "hit_distance": 9.0,
   "hc_x": 125.5,
   "hc_y": 174.1,
   "would_be_hr_count": 0,
   "inning": 6,
   "play_id": "590995f0-01c3-3011-8ebc-91656ab351b6",
   "venue_id": 12,
   "venue_name": "Tropicana Field",
   "temp_f": 72.0,
   "wind_mph": 0.0,
   "wind_dir": "none",
   "weather_condition": "Dome",
   "distance_flag": false,
   "would_be_hr_flag": false,
   "barrel_score": 0.6,
   "barrel_flag": false,
   "is_home_run": false,
   "is_near_hr": false
  },
  {
   "game_pk": 822958,
   "date": "2026-07-06",
   "player_id": 650490,
   "player_name": "Yandy D\u00edaz",
   "team": "TB",
   "opponent": "NYY",
   "result": "Pop Out",
   "exit_velocity": 89.7,
   "launch_angle": 61.0,
   "hit_distance": 181.0,
   "hc_x": 125.78,
   "hc_y": 195.63,
   "would_be_hr_count": 0,
   "inning": 8,
   "play_id": "46b0b713-fe95-389c-85f4-92a09f8fb771",
   "venue_id": 12,
   "venue_name": "Tropicana Field",
   "temp_f": 72.0,
   "wind_mph": 0.0,
   "wind_dir": "none",
   "weather_condition": "Dome",
   "distance_flag": false,
   "would_be_hr_flag": false,
   "barrel_score": 29.6,
   "barrel_flag": false,
   "is_home_run": false,
   "is_near_hr": false
  },
  {
   "game_pk": 822958,
   "date": "2026-07-06",
   "player_id": 650490,
   "player_name": "Yandy D\u00edaz",
   "team": "TB",
   "opponent": "NYY",
   "result": "Lineout",
   "exit_velocity": 71.7,
   "launch_angle": 13.0,
   "hit_distance": 160.0,
   "hc_x": 141.99,
   "hc_y": 139.66,
   "would_be_hr_count": 0,
   "inning": 3,
   "play_id": "ee15346f-d38b-3e97-8cad-d53c44a6b82e",
   "venue_id": 12,
   "venue_name": "Tropicana Field",
   "temp_f": 72.0,
   "wind_mph": 0.0,
   "wind_dir": "none",
   "weather_condition": "Dome",
   "distance_flag": false,
   "would_be_hr_flag": false,
   "barrel_score": 26.4,
   "barrel_flag": false,
   "is_home_run": false,
   "is_near_hr": false
  },
  {
   "game_pk": 822958,
   "date": "2026-07-06",
   "player_id": 650490,
   "player_name": "Yandy D\u00edaz",
   "team": "TB",
   "opponent": "NYY",
   "result": "Groundout",
   "exit_velocity": 89.9,
   "launch_angle": -17.0,
   "hit_distance": 12.0,
   "hc_x": 128.69,
   "hc_y": 164.42,
   "would_be_hr_count": 0,
   "inning": 1,
   "play_id": "9860c7bc-782a-35b8-adb8-f8d357b9c4ba",
   "venue_id": 12,
   "venue_name": "Tropicana Field",
   "temp_f": 72.0,
   "wind_mph": 0.0,
   "wind_dir": "none",
   "weather_condition": "Dome",
   "distance_flag": false,
   "would_be_hr_flag": false,
   "barrel_score": 18.5,
   "barrel_flag": false,
   "is_home_run": false,
   "is_near_hr": false
  },
  {
   "game_pk": 824172,
   "date": "2026-07-05",
   "player_id": 650490,
   "player_name": "Yandy D\u00edaz",
   "team": "TB",
   "opponent": "HOU",
   "result": "Forceout",
   "exit_velocity": 79.2,
   "launch_angle": -8.0,
   "hit_distance": 21.0,
   "hc_x": 107.4,
   "hc_y": 174.39,
   "would_be_hr_count": 0,
   "inning": 8,
   "play_id": "23851eed-33fe-378b-b273-73a27b355125",
   "venue_id": 2392,
   "venue_name": "Daikin Park",
   "temp_f": 73.0,
   "wind_mph": 0.0,
   "wind_dir": "none",
   "weather_condition": "Roof Closed",
   "distance_flag": false,
   "would_be_hr_flag": false,
   "barrel_score": 9.6,
   "barrel_flag": false,
   "is_home_run": false,
   "is_near_hr": false
  }
 ]
}