{
 "player_id": 666211,
 "player_name": "Taylor Trammell",
 "team": "HOU",
 "as_of": "2026-07-18",
 "form": {
  "streak": 0,
  "frequency": 0.0,
  "slopes": {
   "max_ev": 2.4,
   "parks_sum": 0.0,
   "near_hr": 0.0
  },
  "intensity": 0.333,
  "expectancy_score": 10.0,
  "last_appearance": "2026-07-12"
 },
 "days": [
  {
   "date": "2026-07-12",
   "bbe": 1,
   "hr": 0,
   "near_hr_any": 0,
   "near_hr_xbh": 0,
   "near_hr_distance": 0,
   "near_hr_parks": 0,
   "near_hr_barrel": 0,
   "would_be_hr_parks_sum": 0,
   "max_ev": 93.4,
   "max_distance": 7.0,
   "max_barrel_score": 21.3,
   "temp_f": 74.0,
   "wind_mph": 0.0,
   "wind_dir": "none",
   "weather_condition": "Roof Closed"
  },
  {
   "date": "2026-07-11",
   "bbe": 3,
   "hr": 0,
   "near_hr_any": 0,
   "near_hr_xbh": 0,
   "near_hr_distance": 0,
   "near_hr_parks": 0,
   "near_hr_barrel": 0,
   "would_be_hr_parks_sum": 0,
   "max_ev": 85.9,
   "max_distance": 304.0,
   "max_barrel_score": 51.9,
   "temp_f": 74.0,
   "wind_mph": 0.0,
   "wind_dir": "none",
   "weather_condition": "Roof Closed"
  },
  {
   "date": "2026-07-04",
   "bbe": 2,
   "hr": 0,
   "near_hr_any": 0,
   "near_hr_xbh": 0,
   "near_hr_distance": 0,
   "near_hr_parks": 0,
   "near_hr_barrel": 0,
   "would_be_hr_parks_sum": 0,
   "max_ev": 88.6,
   "max_distance": 322.0,
   "max_barrel_score": 65.3,
   "temp_f": 73.0,
   "wind_mph": 0.0,
   "wind_dir": "none",
   "weather_condition": "Roof Closed"
  }
 ],
 "events": [
  {
   "game_pk": 822876,
   "date": "2026-07-12",
   "player_id": 666211,
   "player_name": "Taylor Trammell",
   "team": "HOU",
   "opponent": "TEX",
   "result": "Groundout",
   "exit_velocity": 93.4,
   "launch_angle": -22.0,
   "hit_distance": 7.0,
   "hc_x": 158.6,
   "hc_y": 164.25,
   "would_be_hr_count": 0,
   "inning": 2,
   "play_id": "14ec5723-8687-3fc4-b458-7e90f3dfd26c",
   "venue_id": 5325,
   "venue_name": "Globe Life Field",
   "temp_f": 74.0,
   "wind_mph": 0.0,
   "wind_dir": "none",
   "weather_condition": "Roof Closed",
   "distance_flag": false,
   "would_be_hr_flag": false,
   "barrel_score": 21.3,
   "barrel_flag": false,
   "is_home_run": false,
   "is_near_hr": false
  },
  {
   "game_pk": 822875,
   "date": "2026-07-11",
   "player_id": 666211,
   "player_name": "Taylor Trammell",
   "team": "HOU",
   "opponent": "TEX",
   "result": "Flyout",
   "exit_velocity": 85.9,
   "launch_angle": 39.0,
   "hit_distance": 304.0,
   "hc_x": 111.19,
   "hc_y": 78.45,
   "would_be_hr_count": 0,
   "inning": 2,
   "play_id": "ce917ed2-3895-39d9-859c-89e6845eb0e8",
   "venue_id": 5325,
   "venue_name": "Globe Life Field",
   "temp_f": 74.0,
   "wind_mph": 0.0,
   "wind_dir": "none",
   "weather_condition": "Roof Closed",
   "distance_flag": false,
   "would_be_hr_flag": false,
   "barrel_score": 51.9,
   "barrel_flag": false,
   "is_home_run": false,
   "is_near_hr": false
  },
  {
   "game_pk": 822875,
   "date": "2026-07-11",
   "player_id": 666211,
   "player_name": "Taylor Trammell",
   "team": "HOU",
   "opponent": "TEX",
   "result": "Lineout",
   "exit_velocity": 81.7,
   "launch_angle": 9.0,
   "hit_distance": 154.0,
   "hc_x": 117.42,
   "hc_y": 140.57,
   "would_be_hr_count": 0,
   "inning": 3,
   "play_id": "6c5ad702-a143-3691-a4fa-bdf3ab2f71a8",
   "venue_id": 5325,
   "venue_name": "Globe Life Field",
   "temp_f": 74.0,
   "wind_mph": 0.0,
   "wind_dir": "none",
   "weather_condition": "Roof Closed",
   "distance_flag": false,
   "would_be_hr_flag": false,
   "barrel_score": 30.5,
   "barrel_flag": false,
   "is_home_run": false,
   "is_near_hr": false
  },
  {
   "game_pk": 822875,
   "date": "2026-07-11",
   "player_id": 666211,
   "player_name": "Taylor Trammell",
   "team": "HOU",
   "opponent": "TEX",
   "result": "Groundout",
   "exit_velocity": 81.4,
   "launch_angle": -1.0,
   "hit_distance": 40.0,
   "hc_x": 157.58,
   "hc_y": 167.3,
   "would_be_hr_count": 0,
   "inning": 8,
   "play_id": "165a87d4-6218-3406-889d-db9c25a2e522",
   "venue_id": 5325,
   "venue_name": "Globe Life Field",
   "temp_f": 74.0,
   "wind_mph": 0.0,
   "wind_dir": "none",
   "weather_condition": "Roof Closed",
   "distance_flag": false,
   "would_be_hr_flag": false,
   "barrel_score": 12.8,
   "barrel_flag": false,
   "is_home_run": false,
   "is_near_hr": false
  },
  {
   "game_pk": 824171,
   "date": "2026-07-04",
   "player_id": 666211,
   "player_name": "Taylor Trammell",
   "team": "HOU",
   "opponent": "TB",
   "result": "Lineout",
   "exit_velocity": 88.6,
   "launch_angle": 25.0,
   "hit_distance": 322.0,
   "hc_x": 102.32,
   "hc_y": 72.14,
   "would_be_hr_count": 0,
   "inning": 2,
   "play_id": "d17cba13-079d-35cb-8c83-1230e4996e3a",
   "venue_id": 2392,
   "venue_name": "Daikin Park",
   "temp_f": 73.0,
   "wind_mph": 0.0,
   "wind_dir": "none",
   "weather_condition": "Roof Closed",
   "distance_flag": false,
   "would_be_hr_flag": false,
   "barrel_score": 65.3,
   "barrel_flag": false,
   "is_home_run": false,
   "is_near_hr": false
  },
  {
   "game_pk": 824171,
   "date": "2026-07-04",
   "player_id": 666211,
   "player_name": "Taylor Trammell",
   "team": "HOU",
   "opponent": "TB",
   "result": "Single",
   "exit_velocity": 70.2,
   "launch_angle": 29.0,
   "hit_distance": 235.0,
   "hc_x": 104.27,
   "hc_y": 102.07,
   "would_be_hr_count": 0,
   "inning": 7,
   "play_id": "7d457237-5900-3c33-b18f-ae98f025d501",
   "venue_id": 2392,
   "venue_name": "Daikin Park",
   "temp_f": 73.0,
   "wind_mph": 0.0,
   "wind_dir": "none",
   "weather_condition": "Roof Closed",
   "distance_flag": false,
   "would_be_hr_flag": false,
   "barrel_score": 44.2,
   "barrel_flag": false,
   "is_home_run": false,
   "is_near_hr": false
  }
 ]
}