{
 "player_id": 691011,
 "player_name": "Drew Romo",
 "team": "CWS",
 "as_of": "2026-07-24",
 "form": {
  "streak": 0,
  "frequency": 0.0,
  "slopes": {
   "max_ev": -0.59,
   "parks_sum": -0.1,
   "near_hr": 0.0
  },
  "intensity": 0.0,
  "expectancy_score": 0.0,
  "last_appearance": "2026-07-21"
 },
 "days": [
  {
   "date": "2026-07-21",
   "bbe": 2,
   "hr": 0,
   "near_hr_any": 0,
   "near_hr_xbh": 0,
   "near_hr_distance": 0,
   "near_hr_parks": 0,
   "near_hr_barrel": 0,
   "would_be_hr_parks_sum": 0,
   "max_ev": 88.4,
   "max_distance": 326.0,
   "max_barrel_score": 67.5,
   "temp_f": 74.0,
   "wind_mph": 0.0,
   "wind_dir": "none",
   "weather_condition": "Roof Closed"
  },
  {
   "date": "2026-07-20",
   "bbe": 3,
   "hr": 0,
   "near_hr_any": 0,
   "near_hr_xbh": 0,
   "near_hr_distance": 0,
   "near_hr_parks": 0,
   "near_hr_barrel": 0,
   "would_be_hr_parks_sum": 0,
   "max_ev": 88.6,
   "max_distance": 245.0,
   "max_barrel_score": 51.4,
   "temp_f": 74.0,
   "wind_mph": 0.0,
   "wind_dir": "none",
   "weather_condition": "Roof Closed"
  },
  {
   "date": "2026-07-19",
   "bbe": 2,
   "hr": 0,
   "near_hr_any": 0,
   "near_hr_xbh": 0,
   "near_hr_distance": 0,
   "near_hr_parks": 0,
   "near_hr_barrel": 0,
   "would_be_hr_parks_sum": 0,
   "max_ev": 78.7,
   "max_distance": 78.0,
   "max_barrel_score": 17.3,
   "temp_f": 68.0,
   "wind_mph": 3.0,
   "wind_dir": "out",
   "weather_condition": "Sunny"
  },
  {
   "date": "2026-07-09",
   "bbe": 2,
   "hr": 0,
   "near_hr_any": 0,
   "near_hr_xbh": 0,
   "near_hr_distance": 0,
   "near_hr_parks": 0,
   "near_hr_barrel": 0,
   "would_be_hr_parks_sum": 1,
   "max_ev": 67.3,
   "max_distance": 137.0,
   "max_barrel_score": 29.7,
   "temp_f": 80.0,
   "wind_mph": 8.0,
   "wind_dir": "out",
   "weather_condition": "Partly Cloudy"
  },
  {
   "date": "2026-07-04",
   "bbe": 2,
   "hr": 0,
   "near_hr_any": 0,
   "near_hr_xbh": 0,
   "near_hr_distance": 0,
   "near_hr_parks": 0,
   "near_hr_barrel": 0,
   "would_be_hr_parks_sum": 0,
   "max_ev": 102.0,
   "max_distance": 269.0,
   "max_barrel_score": 37.8,
   "temp_f": 82.0,
   "wind_mph": 5.0,
   "wind_dir": "in",
   "weather_condition": "Clear"
  }
 ],
 "events": [
  {
   "game_pk": 822871,
   "date": "2026-07-21",
   "player_id": 691011,
   "player_name": "Drew Romo",
   "team": "CWS",
   "opponent": "TEX",
   "result": "Lineout",
   "exit_velocity": 88.4,
   "launch_angle": 27.0,
   "hit_distance": 326.0,
   "hc_x": 64.71,
   "hc_y": 83.09,
   "would_be_hr_count": 0,
   "inning": 8,
   "play_id": "d5ac3154-69e4-34a8-9fdd-84d453208f14",
   "venue_id": 5325,
   "venue_name": "Globe Life Field",
   "temp_f": 74.0,
   "wind_mph": 0.0,
   "wind_dir": "none",
   "weather_condition": "Roof Closed",
   "distance_flag": false,
   "would_be_hr_flag": false,
   "barrel_score": 67.5,
   "barrel_flag": false,
   "is_home_run": false,
   "is_near_hr": false
  },
  {
   "game_pk": 822871,
   "date": "2026-07-21",
   "player_id": 691011,
   "player_name": "Drew Romo",
   "team": "CWS",
   "opponent": "TEX",
   "result": "Flyout",
   "exit_velocity": 71.4,
   "launch_angle": 37.0,
   "hit_distance": 238.0,
   "hc_x": 81.99,
   "hc_y": 115.23,
   "would_be_hr_count": 0,
   "inning": 3,
   "play_id": "0f67519a-307d-340c-bf89-839562a5821c",
   "venue_id": 5325,
   "venue_name": "Globe Life Field",
   "temp_f": 74.0,
   "wind_mph": 0.0,
   "wind_dir": "none",
   "weather_condition": "Roof Closed",
   "distance_flag": false,
   "would_be_hr_flag": false,
   "barrel_score": 36.7,
   "barrel_flag": false,
   "is_home_run": false,
   "is_near_hr": false
  },
  {
   "game_pk": 822874,
   "date": "2026-07-20",
   "player_id": 691011,
   "player_name": "Drew Romo",
   "team": "CWS",
   "opponent": "TEX",
   "result": "Double",
   "exit_velocity": 88.6,
   "launch_angle": 17.0,
   "hit_distance": 245.0,
   "hc_x": 36.24,
   "hc_y": 119.77,
   "would_be_hr_count": 0,
   "inning": 8,
   "play_id": "10114072-dcbf-3f44-b54c-be9857ab52a0",
   "venue_id": 5325,
   "venue_name": "Globe Life Field",
   "temp_f": 74.0,
   "wind_mph": 0.0,
   "wind_dir": "none",
   "weather_condition": "Roof Closed",
   "distance_flag": false,
   "would_be_hr_flag": false,
   "barrel_score": 51.4,
   "barrel_flag": false,
   "is_home_run": false,
   "is_near_hr": false
  },
  {
   "game_pk": 822874,
   "date": "2026-07-20",
   "player_id": 691011,
   "player_name": "Drew Romo",
   "team": "CWS",
   "opponent": "TEX",
   "result": "Pop Out",
   "exit_velocity": 79.9,
   "launch_angle": 68.0,
   "hit_distance": 153.0,
   "hc_x": 92.19,
   "hc_y": 184.53,
   "would_be_hr_count": 0,
   "inning": 4,
   "play_id": "45b6b02e-1ac1-3e36-924d-8d9a4817ed1d",
   "venue_id": 5325,
   "venue_name": "Globe Life Field",
   "temp_f": 74.0,
   "wind_mph": 0.0,
   "wind_dir": "none",
   "weather_condition": "Roof Closed",
   "distance_flag": false,
   "would_be_hr_flag": false,
   "barrel_score": 19.0,
   "barrel_flag": false,
   "is_home_run": false,
   "is_near_hr": false
  },
  {
   "game_pk": 822874,
   "date": "2026-07-20",
   "player_id": 691011,
   "player_name": "Drew Romo",
   "team": "CWS",
   "opponent": "TEX",
   "result": "Groundout",
   "exit_velocity": 64.7,
   "launch_angle": 9.0,
   "hit_distance": 94.0,
   "hc_x": 144.88,
   "hc_y": 146.11,
   "would_be_hr_count": 0,
   "inning": 5,
   "play_id": "b6240bf5-4720-3902-921e-88aa4aa38405",
   "venue_id": 5325,
   "venue_name": "Globe Life Field",
   "temp_f": 74.0,
   "wind_mph": 0.0,
   "wind_dir": "none",
   "weather_condition": "Roof Closed",
   "distance_flag": false,
   "would_be_hr_flag": false,
   "barrel_score": 16.1,
   "barrel_flag": false,
   "is_home_run": false,
   "is_near_hr": false
  },
  {
   "game_pk": 822786,
   "date": "2026-07-19",
   "player_id": 691011,
   "player_name": "Drew Romo",
   "team": "CWS",
   "opponent": "TOR",
   "result": "Groundout",
   "exit_velocity": 78.7,
   "launch_angle": 4.0,
   "hit_distance": 78.0,
   "hc_x": 114.96,
   "hc_y": 148.01,
   "would_be_hr_count": 0,
   "inning": 7,
   "play_id": "8d95e180-c0ba-3ecb-9ab3-ffd875d47be8",
   "venue_id": 14,
   "venue_name": "Rogers Centre",
   "temp_f": 68.0,
   "wind_mph": 3.0,
   "wind_dir": "out",
   "weather_condition": "Sunny",
   "distance_flag": false,
   "would_be_hr_flag": false,
   "barrel_score": 17.3,
   "barrel_flag": false,
   "is_home_run": false,
   "is_near_hr": false
  },
  {
   "game_pk": 822786,
   "date": "2026-07-19",
   "player_id": 691011,
   "player_name": "Drew Romo",
   "team": "CWS",
   "opponent": "TOR",
   "result": "Pop Out",
   "exit_velocity": 66.9,
   "launch_angle": 88.0,
   "hit_distance": 24.0,
   "hc_x": 119.8,
   "hc_y": 213.37,
   "would_be_hr_count": 0,
   "inning": 3,
   "play_id": "39552c70-a238-3bc1-b162-86dbb0bdc6d1",
   "venue_id": 14,
   "venue_name": "Rogers Centre",
   "temp_f": 68.0,
   "wind_mph": 3.0,
   "wind_dir": "out",
   "weather_condition": "Sunny",
   "distance_flag": false,
   "would_be_hr_flag": false,
   "barrel_score": 1.6,
   "barrel_flag": false,
   "is_home_run": false,
   "is_near_hr": false
  },
  {
   "game_pk": 824577,
   "date": "2026-07-09",
   "player_id": 691011,
   "player_name": "Drew Romo",
   "team": "CWS",
   "opponent": "BOS",
   "result": "Bunt Lineout",
   "exit_velocity": 42.3,
   "launch_angle": 22.0,
   "hit_distance": 85.0,
   "hc_x": 153.13,
   "hc_y": 181.45,
   "would_be_hr_count": 0,
   "inning": 5,
   "play_id": "e6af773d-c008-35ed-9ffc-03d8d5bbf47a",
   "venue_id": 4,
   "venue_name": "Rate Field",
   "temp_f": 80.0,
   "wind_mph": 8.0,
   "wind_dir": "out",
   "weather_condition": "Partly Cloudy",
   "distance_flag": false,
   "would_be_hr_flag": false,
   "barrel_score": 29.7,
   "barrel_flag": false,
   "is_home_run": false,
   "is_near_hr": false
  },
  {
   "game_pk": 824577,
   "date": "2026-07-09",
   "player_id": 691011,
   "player_name": "Drew Romo",
   "team": "CWS",
   "opponent": "BOS",
   "result": "Pop Out",
   "exit_velocity": 67.3,
   "launch_angle": 64.0,
   "hit_distance": 137.0,
   "hc_x": 141.78,
   "hc_y": 149.6,
   "would_be_hr_count": 1,
   "inning": 3,
   "play_id": "ff8da63e-30e0-37b0-80b8-46c5fcb91699",
   "venue_id": 4,
   "venue_name": "Rate Field",
   "temp_f": 80.0,
   "wind_mph": 8.0,
   "wind_dir": "out",
   "weather_condition": "Partly Cloudy",
   "distance_flag": false,
   "would_be_hr_flag": false,
   "barrel_score": 9.1,
   "barrel_flag": false,
   "is_home_run": false,
   "is_near_hr": false
  },
  {
   "game_pk": 824415,
   "date": "2026-07-04",
   "player_id": 691011,
   "player_name": "Drew Romo",
   "team": "CWS",
   "opponent": "CLE",
   "result": "Flyout",
   "exit_velocity": 88.7,
   "launch_angle": 52.0,
   "hit_distance": 269.0,
   "hc_x": 45.47,
   "hc_y": 126.2,
   "would_be_hr_count": 0,
   "inning": 6,
   "play_id": "bdaa2914-e5e6-3cba-9073-97c5a59a2c5d",
   "venue_id": 5,
   "venue_name": "Progressive Field",
   "temp_f": 82.0,
   "wind_mph": 5.0,
   "wind_dir": "in",
   "weather_condition": "Clear",
   "distance_flag": false,
   "would_be_hr_flag": false,
   "barrel_score": 37.8,
   "barrel_flag": false,
   "is_home_run": false,
   "is_near_hr": false
  },
  {
   "game_pk": 824415,
   "date": "2026-07-04",
   "player_id": 691011,
   "player_name": "Drew Romo",
   "team": "CWS",
   "opponent": "CLE",
   "result": "Single",
   "exit_velocity": 102.0,
   "launch_angle": null,
   "hit_distance": 61.0,
   "hc_x": 95.17,
   "hc_y": 151.96,
   "would_be_hr_count": 0,
   "inning": 2,
   "play_id": "84e2f883-546c-3a69-bf28-5174e4c94db1",
   "venue_id": 5,
   "venue_name": "Progressive Field",
   "temp_f": 82.0,
   "wind_mph": 5.0,
   "wind_dir": "in",
   "weather_condition": "Clear",
   "distance_flag": false,
   "would_be_hr_flag": false,
   "barrel_score": 32.5,
   "barrel_flag": false,
   "is_home_run": false,
   "is_near_hr": false
  }
 ]
}