{
 "player_id": 695578,
 "player_name": "James Wood",
 "team": "WSH",
 "as_of": "2026-07-21",
 "form": {
  "streak": 0,
  "frequency": 0.0,
  "slopes": {
   "max_ev": 3.846,
   "parks_sum": 0.0,
   "near_hr": 0.0
  },
  "intensity": 0.333,
  "expectancy_score": 10.0,
  "last_appearance": "2026-07-19"
 },
 "days": [
  {
   "date": "2026-07-19",
   "bbe": 2,
   "hr": 0,
   "near_hr_any": 0,
   "near_hr_xbh": 0,
   "near_hr_distance": 0,
   "near_hr_parks": 0,
   "near_hr_barrel": 0,
   "would_be_hr_parks_sum": 0,
   "max_ev": 108.6,
   "max_distance": 174.0,
   "max_barrel_score": 54.3,
   "temp_f": 86.0,
   "wind_mph": 3.0,
   "wind_dir": "out",
   "weather_condition": "Partly Cloudy"
  },
  {
   "date": "2026-07-18",
   "bbe": 1,
   "hr": 0,
   "near_hr_any": 0,
   "near_hr_xbh": 0,
   "near_hr_distance": 0,
   "near_hr_parks": 0,
   "near_hr_barrel": 0,
   "would_be_hr_parks_sum": 0,
   "max_ev": 100.3,
   "max_distance": 30.0,
   "max_barrel_score": 28.9,
   "temp_f": 88.0,
   "wind_mph": 9.0,
   "wind_dir": "out",
   "weather_condition": "Clear"
  },
  {
   "date": "2026-07-17",
   "bbe": 1,
   "hr": 0,
   "near_hr_any": 0,
   "near_hr_xbh": 0,
   "near_hr_distance": 0,
   "near_hr_parks": 0,
   "near_hr_barrel": 0,
   "would_be_hr_parks_sum": 0,
   "max_ev": 96.0,
   "max_distance": 39.0,
   "max_barrel_score": 25.7,
   "temp_f": 85.0,
   "wind_mph": 11.0,
   "wind_dir": "out",
   "weather_condition": "Clear"
  },
  {
   "date": "2026-07-12",
   "bbe": 1,
   "hr": 1,
   "near_hr_any": 0,
   "near_hr_xbh": 0,
   "near_hr_distance": 0,
   "near_hr_parks": 0,
   "near_hr_barrel": 0,
   "would_be_hr_parks_sum": 0,
   "max_ev": 110.0,
   "max_distance": 434.0,
   "max_barrel_score": 92.9,
   "temp_f": 83.0,
   "wind_mph": 7.0,
   "wind_dir": "in",
   "weather_condition": "Partly Cloudy"
  },
  {
   "date": "2026-07-11",
   "bbe": 4,
   "hr": 1,
   "near_hr_any": 0,
   "near_hr_xbh": 0,
   "near_hr_distance": 0,
   "near_hr_parks": 0,
   "near_hr_barrel": 0,
   "would_be_hr_parks_sum": 0,
   "max_ev": 100.4,
   "max_distance": 388.0,
   "max_barrel_score": 72.5,
   "temp_f": 86.0,
   "wind_mph": 3.0,
   "wind_dir": "in",
   "weather_condition": "Partly Cloudy"
  },
  {
   "date": "2026-07-10",
   "bbe": 5,
   "hr": 1,
   "near_hr_any": 0,
   "near_hr_xbh": 0,
   "near_hr_distance": 0,
   "near_hr_parks": 0,
   "near_hr_barrel": 0,
   "would_be_hr_parks_sum": 0,
   "max_ev": 111.9,
   "max_distance": 419.0,
   "max_barrel_score": 88.9,
   "temp_f": 79.0,
   "wind_mph": 5.0,
   "wind_dir": "out",
   "weather_condition": "Partly Cloudy"
  },
  {
   "date": "2026-07-08",
   "bbe": 1,
   "hr": 0,
   "near_hr_any": 0,
   "near_hr_xbh": 0,
   "near_hr_distance": 0,
   "near_hr_parks": 0,
   "near_hr_barrel": 0,
   "would_be_hr_parks_sum": 0,
   "max_ev": 63.5,
   "max_distance": 6.0,
   "max_barrel_score": 0.4,
   "temp_f": 84.0,
   "wind_mph": 5.0,
   "wind_dir": "cross",
   "weather_condition": "Partly Cloudy"
  },
  {
   "date": "2026-07-07",
   "bbe": 3,
   "hr": 1,
   "near_hr_any": 0,
   "near_hr_xbh": 0,
   "near_hr_distance": 0,
   "near_hr_parks": 0,
   "near_hr_barrel": 0,
   "would_be_hr_parks_sum": 0,
   "max_ev": 111.4,
   "max_distance": 419.0,
   "max_barrel_score": 90.9,
   "temp_f": 82.0,
   "wind_mph": 4.0,
   "wind_dir": "in",
   "weather_condition": "Cloudy"
  },
  {
   "date": "2026-07-06",
   "bbe": 2,
   "hr": 1,
   "near_hr_any": 0,
   "near_hr_xbh": 0,
   "near_hr_distance": 0,
   "near_hr_parks": 0,
   "near_hr_barrel": 0,
   "would_be_hr_parks_sum": 0,
   "max_ev": 109.8,
   "max_distance": 446.0,
   "max_barrel_score": 90.2,
   "temp_f": 80.0,
   "wind_mph": 2.0,
   "wind_dir": "out",
   "weather_condition": "Overcast"
  },
  {
   "date": "2026-07-05",
   "bbe": 3,
   "hr": 0,
   "near_hr_any": 0,
   "near_hr_xbh": 0,
   "near_hr_distance": 0,
   "near_hr_parks": 0,
   "near_hr_barrel": 0,
   "would_be_hr_parks_sum": 0,
   "max_ev": 97.5,
   "max_distance": 315.0,
   "max_barrel_score": 65.1,
   "temp_f": 92.0,
   "wind_mph": 2.0,
   "wind_dir": "out",
   "weather_condition": "Partly Cloudy"
  },
  {
   "date": "2026-07-04",
   "bbe": 2,
   "hr": 1,
   "near_hr_any": 0,
   "near_hr_xbh": 0,
   "near_hr_distance": 0,
   "near_hr_parks": 0,
   "near_hr_barrel": 0,
   "would_be_hr_parks_sum": 0,
   "max_ev": 113.1,
   "max_distance": 428.0,
   "max_barrel_score": 93.0,
   "temp_f": 93.0,
   "wind_mph": 5.0,
   "wind_dir": "in",
   "weather_condition": "Sunny"
  }
 ],
 "events": [
  {
   "game_pk": 824978,
   "date": "2026-07-19",
   "player_id": 695578,
   "player_name": "James Wood",
   "team": "WSH",
   "opponent": "ATH",
   "result": "Lineout",
   "exit_velocity": 108.2,
   "launch_angle": 8.0,
   "hit_distance": 174.0,
   "hc_x": 119.57,
   "hc_y": 144.93,
   "would_be_hr_count": 0,
   "inning": 5,
   "play_id": "3fb1278c-360c-33e5-a1b0-bde4e21a240d",
   "venue_id": 2529,
   "venue_name": "Sutter Health Park",
   "temp_f": 86.0,
   "wind_mph": 3.0,
   "wind_dir": "out",
   "weather_condition": "Partly Cloudy",
   "distance_flag": false,
   "would_be_hr_flag": false,
   "barrel_score": 54.3,
   "barrel_flag": false,
   "is_home_run": false,
   "is_near_hr": false
  },
  {
   "game_pk": 824978,
   "date": "2026-07-19",
   "player_id": 695578,
   "player_name": "James Wood",
   "team": "WSH",
   "opponent": "ATH",
   "result": "Groundout",
   "exit_velocity": 108.6,
   "launch_angle": 3.0,
   "hit_distance": 85.0,
   "hc_x": 147.46,
   "hc_y": 142.9,
   "would_be_hr_count": 0,
   "inning": 8,
   "play_id": "4a405f89-2a67-3d4f-be0e-3c49eafffae6",
   "venue_id": 2529,
   "venue_name": "Sutter Health Park",
   "temp_f": 86.0,
   "wind_mph": 3.0,
   "wind_dir": "out",
   "weather_condition": "Partly Cloudy",
   "distance_flag": false,
   "would_be_hr_flag": false,
   "barrel_score": 43.3,
   "barrel_flag": false,
   "is_home_run": false,
   "is_near_hr": false
  },
  {
   "game_pk": 824979,
   "date": "2026-07-18",
   "player_id": 695578,
   "player_name": "James Wood",
   "team": "WSH",
   "opponent": "ATH",
   "result": "Groundout",
   "exit_velocity": 100.3,
   "launch_angle": -4.0,
   "hit_distance": 30.0,
   "hc_x": 151.52,
   "hc_y": 171.3,
   "would_be_hr_count": 0,
   "inning": 6,
   "play_id": "4dd9acca-cb92-30c6-b029-68fd45e4f41e",
   "venue_id": 2529,
   "venue_name": "Sutter Health Park",
   "temp_f": 88.0,
   "wind_mph": 9.0,
   "wind_dir": "out",
   "weather_condition": "Clear",
   "distance_flag": false,
   "would_be_hr_flag": false,
   "barrel_score": 28.9,
   "barrel_flag": false,
   "is_home_run": false,
   "is_near_hr": false
  },
  {
   "game_pk": 824981,
   "date": "2026-07-17",
   "player_id": 695578,
   "player_name": "James Wood",
   "team": "WSH",
   "opponent": "ATH",
   "result": "Single",
   "exit_velocity": 96.0,
   "launch_angle": -1.0,
   "hit_distance": 39.0,
   "hc_x": 158.9,
   "hc_y": 121.79,
   "would_be_hr_count": 0,
   "inning": 6,
   "play_id": "d572385e-4051-3547-bb1a-4c9441fc371d",
   "venue_id": 2529,
   "venue_name": "Sutter Health Park",
   "temp_f": 85.0,
   "wind_mph": 11.0,
   "wind_dir": "out",
   "weather_condition": "Clear",
   "distance_flag": false,
   "would_be_hr_flag": false,
   "barrel_score": 25.7,
   "barrel_flag": false,
   "is_home_run": false,
   "is_near_hr": false
  },
  {
   "game_pk": 822708,
   "date": "2026-07-12",
   "player_id": 695578,
   "player_name": "James Wood",
   "team": "WSH",
   "opponent": "NYY",
   "result": "Home Run",
   "exit_velocity": 110.0,
   "launch_angle": 26.0,
   "hit_distance": 434.0,
   "hc_x": 145.74,
   "hc_y": 24.14,
   "would_be_hr_count": 29,
   "inning": 1,
   "play_id": "1a926577-7001-3ba4-b804-d98cb9035f0b",
   "venue_id": 3309,
   "venue_name": "Nationals Park",
   "temp_f": 83.0,
   "wind_mph": 7.0,
   "wind_dir": "in",
   "weather_condition": "Partly Cloudy",
   "distance_flag": false,
   "would_be_hr_flag": false,
   "barrel_score": 92.9,
   "barrel_flag": false,
   "is_home_run": true,
   "is_near_hr": false
  },
  {
   "game_pk": 822711,
   "date": "2026-07-11",
   "player_id": 695578,
   "player_name": "James Wood",
   "team": "WSH",
   "opponent": "NYY",
   "result": "Home Run",
   "exit_velocity": 100.4,
   "launch_angle": 37.0,
   "hit_distance": 388.0,
   "hc_x": 196.63,
   "hc_y": 58.81,
   "would_be_hr_count": 30,
   "inning": 1,
   "play_id": "d8d54966-3b07-315f-88d1-2a3f7a78af42",
   "venue_id": 3309,
   "venue_name": "Nationals Park",
   "temp_f": 86.0,
   "wind_mph": 3.0,
   "wind_dir": "in",
   "weather_condition": "Partly Cloudy",
   "distance_flag": false,
   "would_be_hr_flag": false,
   "barrel_score": 72.5,
   "barrel_flag": false,
   "is_home_run": true,
   "is_near_hr": false
  },
  {
   "game_pk": 822711,
   "date": "2026-07-11",
   "player_id": 695578,
   "player_name": "James Wood",
   "team": "WSH",
   "opponent": "NYY",
   "result": "Single",
   "exit_velocity": 69.1,
   "launch_angle": 31.0,
   "hit_distance": 213.0,
   "hc_x": 79.7,
   "hc_y": 128.62,
   "would_be_hr_count": 0,
   "inning": 9,
   "play_id": "6aec09f5-95a1-3387-a22c-de2edb8e2478",
   "venue_id": 3309,
   "venue_name": "Nationals Park",
   "temp_f": 86.0,
   "wind_mph": 3.0,
   "wind_dir": "in",
   "weather_condition": "Partly Cloudy",
   "distance_flag": false,
   "would_be_hr_flag": false,
   "barrel_score": 40.4,
   "barrel_flag": false,
   "is_home_run": false,
   "is_near_hr": false
  },
  {
   "game_pk": 822711,
   "date": "2026-07-11",
   "player_id": 695578,
   "player_name": "James Wood",
   "team": "WSH",
   "opponent": "NYY",
   "result": "Groundout",
   "exit_velocity": 90.8,
   "launch_angle": -8.0,
   "hit_distance": 16.0,
   "hc_x": 150.06,
   "hc_y": 151.18,
   "would_be_hr_count": 0,
   "inning": 3,
   "play_id": "bf0ee318-ef41-3354-858b-512effc9b180",
   "venue_id": 3309,
   "venue_name": "Nationals Park",
   "temp_f": 86.0,
   "wind_mph": 3.0,
   "wind_dir": "in",
   "weather_condition": "Partly Cloudy",
   "distance_flag": false,
   "would_be_hr_flag": false,
   "barrel_score": 19.6,
   "barrel_flag": false,
   "is_home_run": false,
   "is_near_hr": false
  },
  {
   "game_pk": 822711,
   "date": "2026-07-11",
   "player_id": 695578,
   "player_name": "James Wood",
   "team": "WSH",
   "opponent": "NYY",
   "result": "Single",
   "exit_velocity": 81.2,
   "launch_angle": -11.0,
   "hit_distance": 11.0,
   "hc_x": 116.11,
   "hc_y": 180.06,
   "would_be_hr_count": 0,
   "inning": 7,
   "play_id": "6d90bf2c-9d43-3f26-9c21-2dfb09b7bca5",
   "venue_id": 3309,
   "venue_name": "Nationals Park",
   "temp_f": 86.0,
   "wind_mph": 3.0,
   "wind_dir": "in",
   "weather_condition": "Partly Cloudy",
   "distance_flag": false,
   "would_be_hr_flag": false,
   "barrel_score": 10.7,
   "barrel_flag": false,
   "is_home_run": false,
   "is_near_hr": false
  },
  {
   "game_pk": 822709,
   "date": "2026-07-10",
   "player_id": 695578,
   "player_name": "James Wood",
   "team": "WSH",
   "opponent": "NYY",
   "result": "Home Run",
   "exit_velocity": 105.5,
   "launch_angle": 27.0,
   "hit_distance": 419.0,
   "hc_x": 173.8,
   "hc_y": 35.95,
   "would_be_hr_count": 30,
   "inning": 7,
   "play_id": "4fbf8caa-b144-3656-b334-bd7ee5f79acc",
   "venue_id": 3309,
   "venue_name": "Nationals Park",
   "temp_f": 79.0,
   "wind_mph": 5.0,
   "wind_dir": "out",
   "weather_condition": "Partly Cloudy",
   "distance_flag": false,
   "would_be_hr_flag": false,
   "barrel_score": 88.9,
   "barrel_flag": false,
   "is_home_run": true,
   "is_near_hr": false
  },
  {
   "game_pk": 822709,
   "date": "2026-07-10",
   "player_id": 695578,
   "player_name": "James Wood",
   "team": "WSH",
   "opponent": "NYY",
   "result": "Double",
   "exit_velocity": 111.9,
   "launch_angle": 2.0,
   "hit_distance": 72.0,
   "hc_x": 151.05,
   "hc_y": 83.57,
   "would_be_hr_count": 0,
   "inning": 3,
   "play_id": "9d63583f-14e8-3d69-969d-4ffad8d5f921",
   "venue_id": 3309,
   "venue_name": "Nationals Park",
   "temp_f": 79.0,
   "wind_mph": 5.0,
   "wind_dir": "out",
   "weather_condition": "Partly Cloudy",
   "distance_flag": false,
   "would_be_hr_flag": false,
   "barrel_score": 44.2,
   "barrel_flag": false,
   "is_home_run": false,
   "is_near_hr": false
  },
  {
   "game_pk": 822709,
   "date": "2026-07-10",
   "player_id": 695578,
   "player_name": "James Wood",
   "team": "WSH",
   "opponent": "NYY",
   "result": "Single",
   "exit_velocity": 106.0,
   "launch_angle": -19.0,
   "hit_distance": 8.0,
   "hc_x": 140.9,
   "hc_y": 86.61,
   "would_be_hr_count": 0,
   "inning": 1,
   "play_id": "2438d94a-3055-35af-a782-c5f86d0e63c1",
   "venue_id": 3309,
   "venue_name": "Nationals Park",
   "temp_f": 79.0,
   "wind_mph": 5.0,
   "wind_dir": "out",
   "weather_condition": "Partly Cloudy",
   "distance_flag": false,
   "would_be_hr_flag": false,
   "barrel_score": 32.5,
   "barrel_flag": false,
   "is_home_run": false,
   "is_near_hr": false
  },
  {
   "game_pk": 822709,
   "date": "2026-07-10",
   "player_id": 695578,
   "player_name": "James Wood",
   "team": "WSH",
   "opponent": "NYY",
   "result": "Groundout",
   "exit_velocity": 101.7,
   "launch_angle": -4.0,
   "hit_distance": 31.0,
   "hc_x": 153.07,
   "hc_y": 146.96,
   "would_be_hr_count": 0,
   "inning": 5,
   "play_id": "5007fd06-7d61-34d9-ae3d-7ae724fce634",
   "venue_id": 3309,
   "venue_name": "Nationals Park",
   "temp_f": 79.0,
   "wind_mph": 5.0,
   "wind_dir": "out",
   "weather_condition": "Partly Cloudy",
   "distance_flag": false,
   "would_be_hr_flag": false,
   "barrel_score": 30.2,
   "barrel_flag": false,
   "is_home_run": false,
   "is_near_hr": false
  },
  {
   "game_pk": 822709,
   "date": "2026-07-10",
   "player_id": 695578,
   "player_name": "James Wood",
   "team": "WSH",
   "opponent": "NYY",
   "result": "Groundout",
   "exit_velocity": 52.3,
   "launch_angle": -70.0,
   "hit_distance": 4.0,
   "hc_x": 120.8,
   "hc_y": 183.62,
   "would_be_hr_count": 0,
   "inning": 9,
   "play_id": "953b814b-30a6-3206-b534-bfdb68e151ad",
   "venue_id": 3309,
   "venue_name": "Nationals Park",
   "temp_f": 79.0,
   "wind_mph": 5.0,
   "wind_dir": "out",
   "weather_condition": "Partly Cloudy",
   "distance_flag": false,
   "would_be_hr_flag": false,
   "barrel_score": 0.3,
   "barrel_flag": false,
   "is_home_run": false,
   "is_near_hr": false
  },
  {
   "game_pk": 822710,
   "date": "2026-07-08",
   "player_id": 695578,
   "player_name": "James Wood",
   "team": "WSH",
   "opponent": "HOU",
   "result": "Groundout",
   "exit_velocity": 63.5,
   "launch_angle": -32.0,
   "hit_distance": 6.0,
   "hc_x": 99.27,
   "hc_y": 165.9,
   "would_be_hr_count": 0,
   "inning": 5,
   "play_id": "fac961bb-de82-3c43-93bd-76fad045de26",
   "venue_id": 3309,
   "venue_name": "Nationals Park",
   "temp_f": 84.0,
   "wind_mph": 5.0,
   "wind_dir": "cross",
   "weather_condition": "Partly Cloudy",
   "distance_flag": false,
   "would_be_hr_flag": false,
   "barrel_score": 0.4,
   "barrel_flag": false,
   "is_home_run": false,
   "is_near_hr": false
  },
  {
   "game_pk": 822713,
   "date": "2026-07-07",
   "player_id": 695578,
   "player_name": "James Wood",
   "team": "WSH",
   "opponent": "HOU",
   "result": "Home Run",
   "exit_velocity": 111.4,
   "launch_angle": 24.0,
   "hit_distance": 419.0,
   "hc_x": 192.2,
   "hc_y": 42.63,
   "would_be_hr_count": 29,
   "inning": 1,
   "play_id": "03416aeb-69dc-3c02-8179-2c516252d88d",
   "venue_id": 3309,
   "venue_name": "Nationals Park",
   "temp_f": 82.0,
   "wind_mph": 4.0,
   "wind_dir": "in",
   "weather_condition": "Cloudy",
   "distance_flag": false,
   "would_be_hr_flag": false,
   "barrel_score": 90.9,
   "barrel_flag": false,
   "is_home_run": true,
   "is_near_hr": false
  },
  {
   "game_pk": 822713,
   "date": "2026-07-07",
   "player_id": 695578,
   "player_name": "James Wood",
   "team": "WSH",
   "opponent": "HOU",
   "result": "Single",
   "exit_velocity": 100.8,
   "launch_angle": 2.0,
   "hit_distance": 60.0,
   "hc_x": 172.85,
   "hc_y": 102.84,
   "would_be_hr_count": 0,
   "inning": 9,
   "play_id": "d29ba831-146b-30d3-ac65-1115cd7c48f6",
   "venue_id": 3309,
   "venue_name": "Nationals Park",
   "temp_f": 82.0,
   "wind_mph": 4.0,
   "wind_dir": "in",
   "weather_condition": "Cloudy",
   "distance_flag": false,
   "would_be_hr_flag": false,
   "barrel_score": 33.6,
   "barrel_flag": false,
   "is_home_run": false,
   "is_near_hr": false
  },
  {
   "game_pk": 822713,
   "date": "2026-07-07",
   "player_id": 695578,
   "player_name": "James Wood",
   "team": "WSH",
   "opponent": "HOU",
   "result": "Groundout",
   "exit_velocity": 93.3,
   "launch_angle": -2.0,
   "hit_distance": 31.0,
   "hc_x": 156.74,
   "hc_y": 165.99,
   "would_be_hr_count": 0,
   "inning": 7,
   "play_id": "6450cf04-a589-3999-8bba-f76c88f8bf15",
   "venue_id": 3309,
   "venue_name": "Nationals Park",
   "temp_f": 82.0,
   "wind_mph": 4.0,
   "wind_dir": "in",
   "weather_condition": "Cloudy",
   "distance_flag": false,
   "would_be_hr_flag": false,
   "barrel_score": 22.8,
   "barrel_flag": false,
   "is_home_run": false,
   "is_near_hr": false
  },
  {
   "game_pk": 822712,
   "date": "2026-07-06",
   "player_id": 695578,
   "player_name": "James Wood",
   "team": "WSH",
   "opponent": "HOU",
   "result": "Home Run",
   "exit_velocity": 109.8,
   "launch_angle": 32.0,
   "hit_distance": 446.0,
   "hc_x": 103.99,
   "hc_y": 19.68,
   "would_be_hr_count": 30,
   "inning": 5,
   "play_id": "a68fd4ff-9af9-37fb-8e10-57648c7ac052",
   "venue_id": 3309,
   "venue_name": "Nationals Park",
   "temp_f": 80.0,
   "wind_mph": 2.0,
   "wind_dir": "out",
   "weather_condition": "Overcast",
   "distance_flag": false,
   "would_be_hr_flag": false,
   "barrel_score": 90.2,
   "barrel_flag": false,
   "is_home_run": true,
   "is_near_hr": false
  },
  {
   "game_pk": 822712,
   "date": "2026-07-06",
   "player_id": 695578,
   "player_name": "James Wood",
   "team": "WSH",
   "opponent": "HOU",
   "result": "Groundout",
   "exit_velocity": 85.9,
   "launch_angle": null,
   "hit_distance": 41.0,
   "hc_x": 144.49,
   "hc_y": 155.23,
   "would_be_hr_count": 0,
   "inning": 4,
   "play_id": "35de6c47-1c00-3964-89a1-f2bb7bdb07d5",
   "venue_id": 3309,
   "venue_name": "Nationals Park",
   "temp_f": 80.0,
   "wind_mph": 2.0,
   "wind_dir": "out",
   "weather_condition": "Overcast",
   "distance_flag": false,
   "would_be_hr_flag": false,
   "barrel_score": 16.9,
   "barrel_flag": false,
   "is_home_run": false,
   "is_near_hr": false
  },
  {
   "game_pk": 822715,
   "date": "2026-07-05",
   "player_id": 695578,
   "player_name": "James Wood",
   "team": "WSH",
   "opponent": "PIT",
   "result": "Lineout",
   "exit_velocity": 97.5,
   "launch_angle": 18.0,
   "hit_distance": 315.0,
   "hc_x": 80.64,
   "hc_y": 98.48,
   "would_be_hr_count": 0,
   "inning": 9,
   "play_id": "f5587413-6570-3177-8b98-45161c20b29b",
   "venue_id": 3309,
   "venue_name": "Nationals Park",
   "temp_f": 92.0,
   "wind_mph": 2.0,
   "wind_dir": "out",
   "weather_condition": "Partly Cloudy",
   "distance_flag": false,
   "would_be_hr_flag": false,
   "barrel_score": 65.1,
   "barrel_flag": false,
   "is_home_run": false,
   "is_near_hr": false
  },
  {
   "game_pk": 822715,
   "date": "2026-07-05",
   "player_id": 695578,
   "player_name": "James Wood",
   "team": "WSH",
   "opponent": "PIT",
   "result": "Groundout",
   "exit_velocity": 85.6,
   "launch_angle": -32.0,
   "hit_distance": 4.0,
   "hc_x": 112.57,
   "hc_y": 174.99,
   "would_be_hr_count": 0,
   "inning": 6,
   "play_id": "d83437a4-1cbc-3fd1-8499-ed0c6370c870",
   "venue_id": 3309,
   "venue_name": "Nationals Park",
   "temp_f": 92.0,
   "wind_mph": 2.0,
   "wind_dir": "out",
   "weather_condition": "Partly Cloudy",
   "distance_flag": false,
   "would_be_hr_flag": false,
   "barrel_score": 14.1,
   "barrel_flag": false,
   "is_home_run": false,
   "is_near_hr": false
  },
  {
   "game_pk": 822715,
   "date": "2026-07-05",
   "player_id": 695578,
   "player_name": "James Wood",
   "team": "WSH",
   "opponent": "PIT",
   "result": "Groundout",
   "exit_velocity": 58.8,
   "launch_angle": -34.0,
   "hit_distance": 6.0,
   "hc_x": 148.06,
   "hc_y": 179.69,
   "would_be_hr_count": 0,
   "inning": 3,
   "play_id": "47273ddf-e90a-31e9-91be-a96edf2bcb79",
   "venue_id": 3309,
   "venue_name": "Nationals Park",
   "temp_f": 92.0,
   "wind_mph": 2.0,
   "wind_dir": "out",
   "weather_condition": "Partly Cloudy",
   "distance_flag": false,
   "would_be_hr_flag": false,
   "barrel_score": 0.4,
   "barrel_flag": false,
   "is_home_run": false,
   "is_near_hr": false
  },
  {
   "game_pk": 822716,
   "date": "2026-07-04",
   "player_id": 695578,
   "player_name": "James Wood",
   "team": "WSH",
   "opponent": "PIT",
   "result": "Home Run",
   "exit_velocity": 113.1,
   "launch_angle": 31.0,
   "hit_distance": 428.0,
   "hc_x": 250.18,
   "hc_y": 75.8,
   "would_be_hr_count": 30,
   "inning": 1,
   "play_id": "23ef8aa8-bce2-307f-8184-c2e2ccc3c45a",
   "venue_id": 3309,
   "venue_name": "Nationals Park",
   "temp_f": 93.0,
   "wind_mph": 5.0,
   "wind_dir": "in",
   "weather_condition": "Sunny",
   "distance_flag": false,
   "would_be_hr_flag": false,
   "barrel_score": 93.0,
   "barrel_flag": false,
   "is_home_run": true,
   "is_near_hr": false
  },
  {
   "game_pk": 822716,
   "date": "2026-07-04",
   "player_id": 695578,
   "player_name": "James Wood",
   "team": "WSH",
   "opponent": "PIT",
   "result": "Groundout",
   "exit_velocity": 98.0,
   "launch_angle": -19.0,
   "hit_distance": 8.0,
   "hc_x": 139.14,
   "hc_y": 145.09,
   "would_be_hr_count": 0,
   "inning": 5,
   "play_id": "10cdd531-ae7a-3f36-aaa6-3e24e3c6a57d",
   "venue_id": 3309,
   "venue_name": "Nationals Park",
   "temp_f": 93.0,
   "wind_mph": 5.0,
   "wind_dir": "in",
   "weather_condition": "Sunny",
   "distance_flag": false,
   "would_be_hr_flag": false,
   "barrel_score": 25.4,
   "barrel_flag": false,
   "is_home_run": false,
   "is_near_hr": false
  }
 ]
}